Workbook

Sheet README
A1: NVIDIA (NVDA) — Dual-Sided Valuation Model
A4: Data as-of 2026-06-22 (project clock). Spot $209.91 · reported P/E 32.15 · 52wk [142.03, 236.54].
A5: Tags: [FACT]=local SEC-XBRL/market brief · [EST]=modeled · [ASSUMPTION]=input · [ATTRIBUTED]=third-party.
A7: SENIOR CALL: LONG-BIASED but two-sided, with entry discipline.
A8: • Accumulate <= ~$195, full size <= ~$180. Do NOT chase at $210 (base case only ~+5% IRR at spot).
A9: • Express the SHORT as a defined-risk put spread + long AVGO/ASIC-basket pair — only on a confirmed
A10: share-loss tell (GM <67% structural, and/or DC rev <+25% YoY, and/or frontier-MoE training off-NVDA).
A12: THE SINGLE TECHNICAL DRIVER: NVDA's retained $ share of the AI-accelerator TAM
A13: (a function of the CUDA + NVLink rack-scale + perf/watt moat vs custom-ASIC inference encroachment,
A14: gated near-term by TSMC CoWoS-L advanced packaging + HBM supply).
A16: SHEETS:
A17: • Assumptions — every input cell, tagged.
... A25: => The bear is loudest on margin (smallest lever); the short only truly works if it is right on SHARE.

Sheet Assumptions
A1: Assumptions (the model's input cells) | H1: engine cells
H2: shares | I2: 24.4
A3: Input | B3: Value | C3: Unit | D3: Tag | E3: Note | H3: dc_pct | I3: 0.88
A4: Spot price | B4: 209.91 | C4: $ | D4: [FACT] | E4: as-of 2026-06-22 | H4: spot | I4: 209.91
A5: Reported P/E (forward) | B5: 32.15 | C5: x | D5: [FACT] | E5: implies ~$6.53 forward EPS
A6: Trailing GAAP EPS (FY26) | B6: 4.9 | C6: $ | D6: [FACT] | E6: 209.91 / 4.90 = 42.8x trailing
A7: FY26 net income | B7: 120.07 | C7: $B | D7: [FACT] | E7: implies ~24.5B diluted shares
A8: Diluted shares | B8: 24.4 | C8: B | D8: [ASSUMPTION] | E8: NI/EPS ~ 24.5B; carry 24.4B
A9: Hold period | B9: 3 | C9: yrs | D9: [ASSUMPTION] | E9: to FY2029; re-underwrite each cadence (Rubin)
A10: Base 2029 accelerator TAM | B10: 440 | C10: $B | D10: [ATTRIBUTED] | E10: mid of ~$350-550B street range
A11: Base retained $ share (driver) | B11: 0.75 | C11: % | D11: [ASSUMPTION] | E11: ASIC inference leakage; frontier held
A12: Datacenter % of revenue | B12: 0.88 | C12: % | D12: [ASSUMPTION] | E12: NVDA ~88% levered to DC AI
A13: Base net margin (FY29) | B13: 0.54 | C13: % | D13: [ASSUMPTION] | E13: haircut from 55.6% FY26 for mix/yield
A14: Base exit multiple | B14: 28 | C14: x | D14: [ASSUMPTION] | E14: de-rate from 32x as growth normalizes

Sheet Revenue_Build
A1: Revenue Build (PxQ) — FY22-FY26 actuals [FACT] + FY27-29 modeled [EST]
A3: Fiscal year | B3: Revenue $B | C3: YoY % | D3: Gross margin | E3: Op margin | F3: Net margin | G3: Net income $B | H3: EPS $ | I3: Tag
A4: FY2022 | B4: 26.91 | C4: 0.614 | D4: 0.649 | E4: 0.373 | F4: 0.362 | G4: 9.75 | H4: 3.85 | I4: [FACT]
A5: FY2023 | B5: 26.97 | C5: 0.002 | D5: 0.569 | E5: 0.157 | F5: 0.162 | G5: 4.37 | H5: 0.17 | I5: [FACT] air-pocket
A6: FY2024 | B6: 60.92 | C6: 1.259 | D6: 0.727 | E6: 0.541 | F6: 0.488 | G6: 29.76 | H6: 1.19 | I6: [FACT]
A7: FY2025 | B7: 130.5 | C7: 1.142 | D7: 0.75 | E7: 0.624 | F7: 0.558 | G7: 72.88 | H7: 2.94 | I7: [FACT]
A8: FY2026 | B8: 215.94 | C8: 0.655 | D8: 0.711 | E8: 0.604 | F8: 0.556 | G8: 120.07 | H8: 4.9 | I8: [FACT]
A9: FY2027E | B9: =B8*1.33 | C9: =B9/B8-1 | D9: 0.7 | E9: 0.59 | F9: 0.55 | G9: =B9*F9 | H9: =G9/Assumptions!I2 | I9: [EST] fwd-implied
A10: FY2028E | B10: =B9*1.28 | C10: =B10/B9-1 | D10: 0.69 | E10: 0.58 | F10: 0.54 | G10: =B10*F10 | H10: =G10/Assumptions!I2 | I10: [EST]
A11: FY2029E | B11: =B10*1.18 | C11: =B11/B10-1 | D11: 0.69 | E11: 0.58 | F11: 0.54 | G11: =B11*F11 | H11: =G11/Assumptions!I2*28 | I11: [EST] base
A13: Base implied price = FY29E EPS x exit multiple (28x): | D13: =Revenue_Build!H11 | E13: =ROUND(H11,0) | F13: =EPS $10.1 x 28x ~= $283 (revenue-path build); pure share*TAM build = $244 (Sensitivity base cell). Band $244-283.
A15: PxQ illustration — the sellable SKU moved UP the value chain:
A16: Discrete data-center GPU (P) | B16: ~$30-35K | D16: [ATTRIBUTED]
A17: GB200 NVL72 rack (P) | B17: ~$3.0M | D17: [ATTRIBUTED]
A18: Vera Rubin NVL72 rack (P) | B18: ~$8.8M | D18: [ATTRIBUTED]
A19: Q (volume) | B19: supply-gated by CoWoS-L + HBM; ~$725B '26 hyperscaler capex | D19: [ATTRIBUTED]

Sheet Sensitivity
A1: AI-Built Sensitivity Matrix — Retained Accelerator Share x 2029 TAM
A2: Single technical driver = NVDA retained $ share of accelerator TAM. Cells (price grid) = canonical published grid; IRR grids are LIVE (=(price/$209.91)^(1/3)-1).
A4: IMPLIED FY2029 PRICE ($)
A5: Retained share \ 2029 TAM | B5: $350B | C5: $440B (base) | D5: $550B
A6: 55% (heavy ASIC) | B6: 143 | C6: 179 | D6: 224
A7: 65% (inference leak) | B7: 168 | C7: 212 | D7: 265
A8: 75% (base) | B8: 194 | C8: 244 | D8: 305
A9: 85% (moat holds) | B9: 220 | C9: 277 | D9: 346
A11: IMPLIED 3-YEAR IRR FROM $209.91 (live)
A12: Retained share \ 2029 TAM | B12: $350B | C12: $440B (base) | D12: $550B
A13: 55% | B13: =(B6/Assumptions!$I$4)^(1/3)-1 | C13: =(C6/Assumptions!$I$4)^(1/3)-1 | D13: =(D6/Assumptions!$I$4)^(1/3)-1
A14: 65% | B14: =(B7/Assumptions!$I$4)^(1/3)-1 | C14: =(C7/Assumptions!$I$4)^(1/3)-1 | D14: =(D7/Assumptions!$I$4)^(1/3)-1
A15: 75% (base) | B15: =(B8/Assumptions!$I$4)^(1/3)-1 | C15: =(C8/Assumptions!$I$4)^(1/3)-1 | D15: =(D8/Assumptions!$I$4)^(1/3)-1
A16: 85% | B16: =(B9/Assumptions!$I$4)^(1/3)-1 | C16: =(C9/Assumptions!$I$4)^(1/3)-1 | D16: =(D9/Assumptions!$I$4)^(1/3)-1
A18: Reading: bottom-left quadrant (share <=65% AND TAM <=$440B) prices NVDA BELOW today's $209.91 over 3 yrs — the short's home turf.
A19: Top-right (share >=75% AND TAM >=$440B) delivers low-double-digit IRRs. Base cell (75% / $440B) = $244 / +5.2% — roughly fairly valued.
A20: The asymmetry sits in the TAILS, which is why the edge is the ENTRY (<=$195), not the thesis at spot.

Sheet Scenarios
A1: Scenarios — Bear / Base / Bull (3-yr, FY2029)
A3: Scenario | B3: Retained share | C3: 2029 TAM $B | D3: Net margin | E3: Exit x | F3: FY29 EPS $ | G3: 3-yr price | H3: 3-yr IRR | I3: Logic
A4: Bear | B4: 0.575 | C4: 325 | D4: 0.49 | E4: 23 | F4: 5.75 | G4: 133 | H4: =(G4/Assumptions!$I$4)^(1/3)-1 | I4: share->55-60%, TAM stalls ~$300-350B on capex digestion; FY23 air-pocket template at 8x the base; circular-financing unwind. PT $124-142.
A5: Base | B5: 0.75 | C5: 440 | D5: 0.54 | E5: 28 | F5: 10.1 | G5: 263 | H5: =(G5/Assumptions!$I$4)^(1/3)-1 | I5: frontier held via NVLink coherence, inference shared with ASICs; GM stabilizes high-60s/low-70s. PT band $244 (pure-share) to $283 (revenue-path).
A6: Bull | B6: 0.85 | C6: 550 | D6: 0.55 | E6: 30 | F6: 12.4 | G6: 359 | H6: =(G6/Assumptions!$I$4)^(1/3)-1 | I6: moat holds broadly, ASICs stay niche; Rubin ramp converts pre-booked CoWoS-L; toward NVDA's own ~$500B Blackwell+Rubin projection. PT $346-372.
A8: Prob-weighted (Base 50 / Bull 30 / Bear 20): ~+9-11% IRR with positive convexity — bull tail > bear tail given the unlevered balance sheet floors downside.

Sheet Valuation
A1: Valuation Bridge — the 32x-vs-43x denominator, reconciled
A3: Item | B3: Value | C3: Tag
A4: Spot price | B4: $209.91 | C4: [FACT]
A5: Reported P/E (forward) | B5: 32.15x | C5: [FACT]
A6: Trailing GAAP EPS (FY26) | B6: $4.90 | C6: [FACT]
A7: Implied forward EPS (209.91/32.15) | B7: ~$6.53 | C7: [EST]
A8: Trailing P/E (209.91/4.90) | B8: 42.8x | C8: [EST]
A9: Fwd/trailing EPS step required | B9: +33% | C9: [EST]
A10: Revenue to hit $6.53 at 55.6% net margin | B10: ~$286B (+33% YoY) | C10: [EST]
A11: ... vs +65.5% FY26 / +114% FY25 just delivered | B11: below-trend bar | C11: [FACT]
A12: Implied diluted shares (NI/EPS) | B12: ~24.5B | C12: [EST]
A13: Market cap (spot x 24.5B) | B13: ~$5.14T | C13: [EST]
A14: PEG (32x / ~50%+ fwd growth) | B14: sub-1.0 | C14: [EST]
A15: Cohort P/E: AMD / MRVL / AVGO / TSM / QCOM | B15: 180.8 / 103.4 / 66.2 / 39.7 / 24.9 | C15: [FACT]
A17: Punchline: 32x and 43x are the SAME valuation on two clocks. The forward multiple sits on an already-decelerated (~+33%) bar, not a heroic one — do not double-count.
