Workbook

Sheet Comps
A1: MLCC peers: comps on the house method (EV / cycle-mean EBITDA)
A2: Local currency, mn. Peer history = 4 fiscal years (Yahoo fundamentals); band = Murata own p25/median/p75 as sector proxy. Yellow = input.
A4: Ticker | B4: Name | C4: Price | D4: Shares (mn) | E4: Net cash | F4: EV | G4: Mean EBITDA | H4: EV / mean EBITDA | I4: Value @ p25 | J4: Value @ median | K4: Value @ p75 | L4: Price vs median value | M4: Fwd P/E | N4: Consensus TP | P4: Band
A5: 6981.T | B5: Murata | C5: ='6981_T'!B16 | D5: ='6981_T'!B17 | E5: ='6981_T'!B18 | F5: ='6981_T'!B19 | G5: ='6981_T'!B20 | H5: ='6981_T'!B21 | I5: ='6981_T'!B22 | J5: ='6981_T'!B23 | K5: ='6981_T'!B24 | L5: =C5/J5-1 | M5: 37.83 | N5: 10414 | P5: p25 | Q5: 10.4
A6: 009150.KS | B6: Samsung Electro-Mechanics | C6: ='009150_KS'!B16 | D6: ='009150_KS'!B17 | E6: ='009150_KS'!B18 | F6: ='009150_KS'!B19 | G6: ='009150_KS'!B20 | H6: ='009150_KS'!B21 | I6: ='009150_KS'!B22 | J6: ='009150_KS'!B23 | K6: ='009150_KS'!B24 | L6: =C6/J6-1 | M6: 47.61 | N6: 2408519 | P6: median | Q6: 11.6
A7: 6976.T | B7: Taiyo Yuden | C7: ='6976_T'!B16 | D7: ='6976_T'!B17 | E7: ='6976_T'!B18 | F7: ='6976_T'!B19 | G7: ='6976_T'!B20 | H7: ='6976_T'!B21 | I7: ='6976_T'!B22 | J7: ='6976_T'!B23 | K7: ='6976_T'!B24 | L7: =C7/J7-1 | M7: 36.35 | N7: 14356 | P7: p75 | Q7: 13.5
A8: 6762.T | B8: TDK | C8: ='6762_T'!B16 | D8: ='6762_T'!B17 | E8: ='6762_T'!B18 | F8: ='6762_T'!B19 | G8: ='6762_T'!B20 | H8: ='6762_T'!B21 | I8: ='6762_T'!B22 | J8: ='6762_T'!B23 | K8: ='6762_T'!B24 | L8: =C8/J8-1 | M8: 22.76 | N8: 4158
A9: 2327.TW | B9: Yageo | C9: ='2327_TW'!B16 | D9: ='2327_TW'!B17 | E9: ='2327_TW'!B18 | F9: ='2327_TW'!B19 | G9: ='2327_TW'!B20 | H9: ='2327_TW'!B21 | I9: ='2327_TW'!B22 | J9: ='2327_TW'!B23 | K9: ='2327_TW'!B24 | L9: =C9/J9-1 | M9: 24.43 | N9: 1009
A10: 6971.T | B10: Kyocera | C10: ='6971_T'!B16 | D10: ='6971_T'!B17 | E10: ='6971_T'!B18 | F10: ='6971_T'!B19 | G10: ='6971_T'!B20 | H10: ='6971_T'!B21 | I10: ='6971_T'!B22 | J10: ='6971_T'!B23 | K10: ='6971_T'!B24 | L10: =C10/J10-1 | M10: 28.89 | N10: 3585
A11: 2492.TW | B11: Walsin Technology | C11: ='2492_TW'!B16 | D11: ='2492_TW'!B17 | E11: ='2492_TW'!B18 | F11: ='2492_TW'!B19 | G11: ='2492_TW'!B20 | H11: ='2492_TW'!B21 | I11: ='2492_TW'!B22 | J11: ='2492_TW'!B23 | K11: ='2492_TW'!B24 | L11: =C11/J11-1 | M11: 21.73
A13: Note: Murata own-band value differs from its tab here because the house model uses 5 FYs from fact books and forecasts to FY3/30.

Sheet 6981_T
A1: Murata (6981.T)
A2: History from Yahoo fundamentals (see data/clean/financials.csv); price/consensus stockanalysis.com 2-Oct-2026.
A4: Metric | B4: FY2022 | C4: FY2023 | D4: FY2024 | E4: FY2025
A5: revenue | B5: 1686796 | C5: 1640158 | D5: 1743352 | E5: 1830856
A6: operating income | B6: 292856 | C6: 215447 | D6: 279702 | E6: 281835
A7: ebitda | B7: 473471 | C7: 419743 | D7: 482514 | E7: 490044
A8: net income | B8: 243946 | C8: 180838 | D8: 233818 | E8: 233920
A9: free cash flow | B9: 80076 | C9: 253409 | D9: 259063 | E9: 173002
A10: capex | B10: -197565 | C10: -236228 | D10: -192842 | E10: -252220
A11: cash | B11: 512420 | C11: 641539 | D11: 675833 | E11: 677886
A12: total debt | B12: 155227 | C12: 105940 | D12: 59993 | E12: 55768
A13: Operating margin | B13: =B6/B5 | C13: =C6/C5 | D13: =D6/D5 | E13: =E6/E5
A16: Price | B16: 8467
A17: Shares (mn) = mcap / price | B17: 1820.007
A18: Net cash (vendor) | B18: 502100
A19: EV | B19: =B16*B17-B18
A20: Mean EBITDA | B20: =AVERAGE(B7:E7)
A21: EV / mean EBITDA | B21: =B19/B20
A22: Value/share @ band p25 | B22: =(Comps!$Q$5*B20+B18)/B17
A23: Value/share @ median | B23: =(Comps!$Q$6*B20+B18)/B17
A24: Value/share @ p75 | B24: =(Comps!$Q$7*B20+B18)/B17
A25: Multiple implied by price | B25: =B21

Sheet 009150_KS
A1: Samsung Electro-Mechanics (009150.KS)
A2: History from Yahoo fundamentals (see data/clean/financials.csv); price/consensus stockanalysis.com 2-Oct-2026.
A4: Metric | B4: FY2022 | C4: FY2023 | D4: FY2024 | E4: FY2025
A5: revenue | B5: 9424551.9 | C5: 8892411.9 | D5: 10294103 | E5: 11314459
A6: operating income | B6: 1183096.8 | C6: 660919.21 | D6: 735135.86 | E6: 913331.18
A7: ebitda | B7: 2111933.4 | C7: 1467592 | D7: 1710219.6 | E7: 1896928.5
A8: net income | B8: 980551.64 | C8: 422956.71 | D8: 679130.07 | E8: 706113.17
A9: free cash flow | B9: 230255.73 | C9: -76491.935 | D9: 603177.85 | E9: 243767.34
A10: capex | B10: -1345100.1 | C10: -1256852.1 | D10: -826641.16 | E10: -1246323.5
A11: cash | B11: 1736672.4 | C11: 1728268.9 | D11: 2027633.8 | E11: 2721160.7
A12: total debt | B12: 1505236.6 | C12: 1596513.1 | D12: 1636007.5 | E12: 2277190.9
A13: Operating margin | B13: =B6/B5 | C13: =C6/C5 | D13: =D6/D5 | E13: =E6/E5
A16: Price | B16: 1581000
A17: Shares (mn) = mcap / price | B17: 73.643
A18: Net cash (vendor) | B18: 240560
A19: EV | B19: =B16*B17-B18
A20: Mean EBITDA | B20: =AVERAGE(B7:E7)
A21: EV / mean EBITDA | B21: =B19/B20
A22: Value/share @ band p25 | B22: =(Comps!$Q$5*B20+B18)/B17
A23: Value/share @ median | B23: =(Comps!$Q$6*B20+B18)/B17
A24: Value/share @ p75 | B24: =(Comps!$Q$7*B20+B18)/B17
A25: Multiple implied by price | B25: =B21

Sheet 6976_T
A1: Taiyo Yuden (6976.T)
A2: History from Yahoo fundamentals (see data/clean/financials.csv); price/consensus stockanalysis.com 2-Oct-2026.
A4: Metric | B4: FY2022 | C4: FY2023 | D4: FY2024 | E4: FY2025
A5: revenue | B5: 319504 | C5: 322647 | D5: 341438 | E5: 355341
A6: operating income | B6: 31981 | C6: 9080 | D6: 10460 | E6: 19996
A7: ebitda | B7: 66468 | C7: 53162 | D7: 55514 | E7: 71073
A8: net income | B8: 23216 | C8: 8317 | D8: 2328 | E8: 14806
A9: free cash flow | B9: 39460 | C9: 51104 | D9: 33941 | E9: 58117
A10: capex
A11: cash | B11: 87197 | C11: 102783 | D11: 78166 | E11: 100072
A12: total debt | B12: 98935 | C12: 148844 | D12: 164400 | E12: 171212
A13: Operating margin | B13: =B6/B5 | C13: =C6/C5 | D13: =D6/D5 | E13: =E6/E5
A16: Price | B16: 10095
A17: Shares (mn) = mcap / price | B17: 129.767
A18: Net cash (vendor) | B18: -49770
A19: EV | B19: =B16*B17-B18
A20: Mean EBITDA | B20: =AVERAGE(B7:E7)
A21: EV / mean EBITDA | B21: =B19/B20
A22: Value/share @ band p25 | B22: =(Comps!$Q$5*B20+B18)/B17
A23: Value/share @ median | B23: =(Comps!$Q$6*B20+B18)/B17
A24: Value/share @ p75 | B24: =(Comps!$Q$7*B20+B18)/B17
A25: Multiple implied by price | B25: =B21

Sheet 6762_T
A1: TDK (6762.T)
A2: History from Yahoo fundamentals (see data/clean/financials.csv); price/consensus stockanalysis.com 2-Oct-2026.
A4: Metric | B4: FY2022 | C4: FY2023 | D4: FY2024 | E4: FY2025
A5: revenue | B5: 2180817 | C5: 2103876 | D5: 2204806 | E5: 2504820
A6: operating income | B6: 168827 | C6: 172893 | D6: 224192 | E6: 272414
A7: ebitda | B7: 394276 | C7: 400011 | D7: 447401 | E7: 513712
A8: net income | B8: 114187 | C8: 124687 | D8: 167161 | E8: 195663
A9: free cash flow | B9: -12937 | C9: 228418 | D9: 220549 | E9: 209081
A10: capex | B10: -275709 | C10: -218589 | D10: -225290 | E10: -298591
A11: cash | B11: 558332 | C11: 697050 | D11: 774611 | E11: 1002362
A12: total debt | B12: 752158 | C12: 685736 | D12: 608400 | E12: 615970
A13: Operating margin | B13: =B6/B5 | C13: =C6/C5 | D13: =D6/D5 | E13: =E6/E5
A16: Price | B16: 3198
A17: Shares (mn) = mcap / price | B17: 1898.061
A18: Net cash (vendor) | B18: 105800
A19: EV | B19: =B16*B17-B18
A20: Mean EBITDA | B20: =AVERAGE(B7:E7)
A21: EV / mean EBITDA | B21: =B19/B20
A22: Value/share @ band p25 | B22: =(Comps!$Q$5*B20+B18)/B17
A23: Value/share @ median | B23: =(Comps!$Q$6*B20+B18)/B17
A24: Value/share @ p75 | B24: =(Comps!$Q$7*B20+B18)/B17
A25: Multiple implied by price | B25: =B21

Sheet 2327_TW
A1: Yageo (2327.TW)
A2: History from Yahoo fundamentals (see data/clean/financials.csv); price/consensus stockanalysis.com 2-Oct-2026.
A4: Metric | B4: FY2022 | C4: FY2023 | D4: FY2024 | E4: FY2025
A5: revenue | B5: 121086.93 | C5: 107609.34 | D5: 121667.33 | E5: 132930.02
A6: operating income | B6: 28987.567 | C6: 20435.452 | D6: 23504.707 | E6: 29808.633
A7: ebitda | B7: 40062.311 | C7: 35251.95 | D7: 39318.056 | E7: 43822.298
A8: net income | B8: 22730.465 | C8: 17427.068 | D8: 19356.484 | E8: 23634.229
A9: free cash flow | B9: 19119.579 | C9: 14210.638 | D9: 24236.198 | E9: 24556.28
A10: capex | B10: -13890.814 | C10: -16856.777 | D10: -6926.174 | E10: -6306.857
A11: cash | B11: 57122.923 | C11: 75926.938 | D11: 101821.59 | E11: 98107.753
A12: total debt | B12: 96238.464 | C12: 137080.71 | D12: 143427.25 | E12: 150894.63
A13: Operating margin | B13: =B6/B5 | C13: =C6/C5 | D13: =D6/D5 | E13: =E6/E5
A16: Price | B16: 626
A17: Shares (mn) = mcap / price | B17: 2060.703
A18: Net cash (vendor) | B18: -46860
A19: EV | B19: =B16*B17-B18
A20: Mean EBITDA | B20: =AVERAGE(B7:E7)
A21: EV / mean EBITDA | B21: =B19/B20
A22: Value/share @ band p25 | B22: =(Comps!$Q$5*B20+B18)/B17
A23: Value/share @ median | B23: =(Comps!$Q$6*B20+B18)/B17
A24: Value/share @ p75 | B24: =(Comps!$Q$7*B20+B18)/B17
A25: Multiple implied by price | B25: =B21

Sheet 6971_T
A1: Kyocera (6971.T)
A2: History from Yahoo fundamentals (see data/clean/financials.csv); price/consensus stockanalysis.com 2-Oct-2026.
A4: Metric | B4: FY2022 | C4: FY2023 | D4: FY2024 | E4: FY2025
A5: revenue | B5: 2025332 | C5: 2004221 | D5: 2014454 | E5: 2070203
A6: operating income | B6: 128517 | C6: 92923 | D6: 26695 | E6: 95021
A7: ebitda | B7: 334040 | C7: 311929 | D7: 252211 | E7: 341085
A8: net income | B8: 127988 | C8: 101074 | D8: 24097 | E8: 140969
A9: free cash flow | B9: -7431 | C9: 109330 | D9: 70074 | E9: 53189
A10: capex | B10: -186643 | C10: -159739 | D10: -167844 | E10: -173046
A11: cash | B11: 396902 | C11: 460333 | D11: 473387 | E11: 490323
A12: total debt | B12: 209801 | C12: 304191 | D12: 342382 | E12: 332724
A13: Operating margin | B13: =B6/B5 | C13: =C6/C5 | D13: =D6/D5 | E13: =E6/E5
A16: Price | B16: 3668
A17: Shares (mn) = mcap / price | B17: 1319.52
A18: Net cash (vendor) | B18: 96950
A19: EV | B19: =B16*B17-B18
A20: Mean EBITDA | B20: =AVERAGE(B7:E7)
A21: EV / mean EBITDA | B21: =B19/B20
A22: Value/share @ band p25 | B22: =(Comps!$Q$5*B20+B18)/B17
A23: Value/share @ median | B23: =(Comps!$Q$6*B20+B18)/B17
A24: Value/share @ p75 | B24: =(Comps!$Q$7*B20+B18)/B17
A25: Multiple implied by price | B25: =B21

Sheet 2492_TW
A1: Walsin Technology (2492.TW)
A2: History from Yahoo fundamentals (see data/clean/financials.csv); price/consensus stockanalysis.com 2-Oct-2026.
A4: Metric | B4: FY2022 | C4: FY2023 | D4: FY2024 | E4: FY2025
A5: revenue | B5: 35297.163 | C5: 32797.671 | D5: 34755.041 | E5: 36462.792
A6: operating income | B6: 2060.933 | C6: 1795.311 | D6: 2182.197 | E6: 2106.005
A7: ebitda | B7: 9374.991 | C7: 8990.409 | D7: 10429.777 | E7: 8492.576
A8: net income | B8: 1650.587 | C8: 1984.596 | D8: 2982.507 | E8: 2298.168
A9: free cash flow | B9: 4161.748 | C9: 6117.578 | D9: 4860.292 | E9: 5059.053
A10: capex | B10: -4770.789 | C10: -2376.139 | D10: -1280.768 | E10: -1086.959
A11: cash | B11: 23650.505 | C11: 20129.096 | D11: 11415.389 | E11: 12567.217
A12: total debt | B12: 26826.031 | C12: 27344.295 | D12: 30549.834 | E12: 30438.492
A13: Operating margin | B13: =B6/B5 | C13: =C6/C5 | D13: =D6/D5 | E13: =E6/E5
A16: Price | B16: 361.5
A17: Shares (mn) = mcap / price | B17: 485.201
A18: Net cash (vendor) | B18: -12810
A19: EV | B19: =B16*B17-B18
A20: Mean EBITDA | B20: =AVERAGE(B7:E7)
A21: EV / mean EBITDA | B21: =B19/B20
A22: Value/share @ band p25 | B22: =(Comps!$Q$5*B20+B18)/B17
A23: Value/share @ median | B23: =(Comps!$Q$6*B20+B18)/B17
A24: Value/share @ p75 | B24: =(Comps!$Q$7*B20+B18)/B17
A25: Multiple implied by price | B25: =B21
